danmu_utils/__init__.py
danmu_utils/common/IConverter.py
danmu_utils/common/IDownloader.py
danmu_utils/common/__init__.py
danmu_utils/common/cmd_interface.py
danmu_utils/common/convert_helper.py
danmu_utils/common/download_helper.py
danmu_utils/common/plugin_collection.py
danmu_utils/common/tmp.py
danmu_utils/plugin/__init__.py
danmu_utils/plugin/bilibili/BilibiliDownloader.py
danmu_utils/plugin/bilibili/BilibiliGenerator.py
danmu_utils/plugin/bilibili/__init__.py
danmu_utils/plugin/bilibili2/Bilibili2Downloader.py
danmu_utils/plugin/bilibili2/Bilibili2ToBilibiliConverter.py
danmu_utils/plugin/bilibili2/__init__.py
danmu_utils/plugin/bilibili2/dm_pb2.py
danmu_utils/plugin/diyidan/DiyidanDownloader.py
danmu_utils/plugin/diyidan/DiyidanToBilibiliConverter.py
danmu_utils/plugin/diyidan/__init__.py
danmu_utils/plugin/iqiyi/IqiyiDownloader.py
danmu_utils/plugin/iqiyi/IqiyiToBilibiliConverter.py
danmu_utils/plugin/iqiyi/__init__.py
danmu_utils/plugin/mgtv/MgtvDownloader.py
danmu_utils/plugin/mgtv/MgtvToBilibiliConverter.py
danmu_utils/plugin/mgtv/__init__.py
danmu_utils/plugin/renrenvideo/RenrenvideoToBilibiliConverter.py
danmu_utils/plugin/renrenvideo/__init__.py
danmu_utils/plugin/vqq/VqqDownloader.py
danmu_utils/plugin/vqq/VqqToBilibiliConverter.py
danmu_utils/plugin/vqq/__init__.py
danmu_utils/plugin/wetv/WetvDownloader.py
danmu_utils/plugin/wetv/WetvToBilibiliConverter.py
danmu_utils/plugin/wetv/__init__.py
danmu_utils/plugin/youku/YoukuDownloader.py
danmu_utils/plugin/youku/YoukuToBilibiliConverter.py
danmu_utils/plugin/youku/__init__.py
danmu_utils-2.12.0.dist-info/LICENSE
danmu_utils-2.12.0.dist-info/METADATA
danmu_utils-2.12.0.dist-info/WHEEL
danmu_utils-2.12.0.dist-info/entry_points.txt
danmu_utils-2.12.0.dist-info/top_level.txt
danmu_utils-2.12.0.dist-info/RECORD
