Metadata-Version: 2.1
Name: danmu-utils
Version: 2.12.0
Summary: Danmu utils support download and convert danmu.
Home-page: https://github.com/Hawthorn2013/danmu_utils
Author: Hawthorn2013
Author-email: hawthorn7dd@hotmail.com
License: UNKNOWN
Platform: UNKNOWN
Classifier: Programming Language :: Python :: 3
Classifier: License :: OSI Approved :: MIT License
Classifier: Operating System :: OS Independent
Requires-Python: >=3.7
Requires-Dist: protobuf
